glassppy.cpython-310-x86_64-linux-gnu.so
glassppy.libs/libgomp-08e37347.so.1.0.0
glassppy-1.0.5.dist-info/RECORD
glassppy-1.0.5.dist-info/top_level.txt
glassppy-1.0.5.dist-info/WHEEL
glassppy-1.0.5.dist-info/METADATA
