Metadata-Version: 2.1
Name: glassppy
Version: 1.0.5
Summary: Graph Library for Approximate Similarity Search
Home-page: UNKNOWN
Author: 
License: UNKNOWN
Platform: UNKNOWN
Requires-Dist: numpy
